vektor/__init__.py
vektor/load_test.py
vektor-0.2.0.dist-info/LICENSE
vektor-0.2.0.dist-info/METADATA
vektor-0.2.0.dist-info/WHEEL
vektor-0.2.0.dist-info/top_level.txt
vektor-0.2.0.dist-info/RECORD
