Metadata-Version: 2.1
Name: vektor
Version: 0.2.0
Summary: Vektor is a library to quickly and easily generate configurable load for web apps.
Author-email: Taimur Ibrahim <tai.him18@gmail.com>
License: MIT
Requires-Python: ==3.12.*
License-File: LICENSE
Requires-Dist: pydantic >=2.8.2
Requires-Dist: tenacity >=8.5.0
Requires-Dist: aiohttp >=3.9.5
Requires-Dist: asyncio >=3.4.3
Requires-Dist: anyio ==4.3.0
Requires-Dist: httpx >=0.27.0
